{"pulled_at": "2019-04-09", "Author": "Pengyuan Li"}
{"pulled_at": "2019-04-08", "Author": "YSP19SCM81M"}
{"pulled_at": "2019-04-07", "Author": "Pengyuan Li"}
{"pulled_at": "2019-04-03", "Author": "Pengyuan Li"}
{"pulled_at": "2019-04-11", "Author": "Junrui Gong"}
{"pulled_at": "2019-04-03", "Author": "PSP19SCM76K"}
{"pulled_at": "2019-04-03", "Author": "Pengyuan Li"}
{"pulled_at": "2019-04-10", "Author": "Pengyuan Li"}
{"pulled_at": "2019-04-02", "Author": "Pengyuan Li"}
{"pulled_at": "2019-04-02", "Author": "Pengyuan Li"}
{"pulled_at": "2019-04-09", "Author": "Pengyuan Li"}
{"pulled_at": "2019-04-01", "Author": "Pengyuan Li"}
{"pulled_at": "2019-04-09", "Author": "Pengyuan Li"}
{"pulled_at": "2019-04-09", "Author": "Pengyuan Li"}
{"pulled_at": "2019-04-09", "Author": "Pengyuan Li"}
{"pulled_at": "2019-04-09", "Author": "Pengyuan Li"}
{"pulled_at": "2019-04-09", "Author": "Pengyuan Li"}
{"pulled_at": "2019-04-09", "Author": "Pengyuan Li"}
{"pulled_at": "2019-04-09", "Author": "Pengyuan Li"}
{"pulled_at": "2019-04-09", "Author": "Pengyuan Li"}
{"pulled_at": "2019-04-09", "Author": "Pengyuan Li"}
{"pulled_at": "2019-04-09", "Author": "Pengyuan Li"}
{"pulled_at": "2019-04-09", "Author": "Pengyuan Li"}
{"pulled_at": "2019-04-09", "Author": "Pengyuan Li"}
{"pulled_at": "2019-04-09", "Author": "Pengyuan Li"}
{"pulled_at": "2019-04-09", "Author": "Pengyuan Li"}
{"pulled_at": "2019-04-09", "Author": "Pengyuan Li"}
{"pulled_at": "2019-04-09", "Author": "Pengyuan Li"}
{"pulled_at": "2019-04-09", "Author": "Pengyuan Li"}
{"pulled_at": "2019-04-09", "Author": "Pengyuan Li"}
{"pulled_at": "2019-04-09", "Author": "Pengyuan Li"}
{"pulled_at": "2019-04-09", "Author": "Pengyuan Li"}
{"pulled_at": "2019-04-09", "Author": "Pengyuan Li"}
{"pulled_at": "2019-04-09", "Author": "Pengyuan Li"}
{"pulled_at": "2019-04-09", "Author": "Pengyuan Li"}
{"pulled_at": "2019-04-09", "Author": "Pengyuan Li"}
{"pulled_at": "2019-04-09", "Author": "Pengyuan Li"}
{"pulled_at": "2019-04-09", "Author": "Pengyuan Li"}
{"pulled_at": "2019-04-09", "Author": "Pengyuan Li"}
{"pulled_at": "2019-04-09", "Author": "Pengyuan Li"}
{"pulled_at": "2019-04-09", "Author": "Pengyuan Li"}
{"pulled_at": "2019-04-08", "Author": "Pengyuan Li"}
{"pulled_at": "2019-04-08", "Author": "Pengyuan Li"}
{"pulled_at": "2019-04-08", "Author": "Pengyuan Li"}
{"pulled_at": "2019-04-08", "Author": "Manasa Kaushik"}
{"pulled_at": "2019-04-08", "Author": "Pengyuan Li"}
{"pulled_at": "2019-04-08", "Author": "Pengyuan Li"}
{"pulled_at": "2019-04-08", "Author": "Pengyuan Li"}
{"pulled_at": "2019-04-08", "Author": "Pengyuan Li"}
{"pulled_at": "2019-04-08", "Author": "Pengyuan Li"}
{"pulled_at": "2019-04-08", "Author": "XSP19SCM71C"}
{"pulled_at": "2019-04-07", "Author": "Pengyuan Li"}
{"pulled_at": "2019-04-07", "Author": "Pengyuan Li"}
{"pulled_at": "2019-04-07", "Author": "Pengyuan Li"}
{"pulled_at": "2019-04-07", "Author": "Pengyuan Li"}
{"pulled_at": "2019-04-07", "Author": "Pengyuan Li"}
{"pulled_at": "2019-04-06", "Author": "Pengyuan Li"}
{"pulled_at": "2019-04-06", "Author": "Pengyuan Li"}
{"pulled_at": "2019-03-29", "Author": "Pengyuan Li"}
{"pulled_at": "2019-04-06", "Author": "MSP19SCM18H"}
{"pulled_at": "2019-04-06", "Author": "shiwanshu kumar"}
{"pulled_at": "2019-04-06", "Author": "Pengyuan Li"}
{"pulled_at": "2019-04-06", "Author": "Pengyuan Li"}
{"pulled_at": "2019-04-05", "Author": "Pengyuan Li"}
{"pulled_at": "2019-04-05", "Author": "ZSP19SCM95D"}
{"pulled_at": "2019-04-05", "Author": "Pengyuan Li"}
{"pulled_at": "2019-04-04", "Author": "WSP19SCM39H"}
{"pulled_at": "2019-04-03", "Author": "Pengyuan Li"}
{"pulled_at": "2019-04-03", "Author": "Pengyuan Li"}
{"pulled_at": "2019-04-03", "Author": "Pengyuan Li"}
{"pulled_at": "2019-04-03", "Author": "Pengyuan Li"}
{"pulled_at": "2019-04-03", "Author": "ASP19SCM61G"}
{"pulled_at": "2019-04-03", "Author": "Pengyuan Li"}
{"pulled_at": "2019-04-03", "Author": "Pengyuan Li"}
{"pulled_at": "2019-04-03", "Author": "Pengyuan Li"}
{"pulled_at": "2019-04-03", "Author": "Pengyuan Li"}
{"pulled_at": "2019-04-03", "Author": "Pengyuan Li"}
{"pulled_at": "2019-04-03", "Author": "Pengyuan Li"}
{"pulled_at": "2019-04-03", "Author": "Pengyuan Li"}
{"pulled_at": "2019-04-03", "Author": "Pengyuan Li"}
{"pulled_at": "2019-04-03", "Author": "Pengyuan Li"}
{"pulled_at": "2019-04-03", "Author": "Pengyuan Li"}
{"pulled_at": "2019-04-03", "Author": "Pengyuan Li"}
{"pulled_at": "2019-04-03", "Author": "Pengyuan Li"}
{"pulled_at": "2019-04-03", "Author": "Pengyuan Li"}
{"pulled_at": "2019-04-03", "Author": "Pengyuan Li"}
{"pulled_at": "2019-04-03", "Author": "Pengyuan Li"}
{"pulled_at": "2019-04-03", "Author": "Pengyuan Li"}
{"pulled_at": "2019-04-03", "Author": "Pengyuan Li"}
{"pulled_at": "2019-04-03", "Author": "Pengyuan Li"}
{"pulled_at": "2019-04-03", "Author": "JSP19SCM59D"}
{"pulled_at": "2019-04-03", "Author": "Pengyuan Li"}
{"pulled_at": "2019-04-03", "Author": "Pengyuan Li"}
{"pulled_at": "2019-04-03", "Author": "Junrui Gong"}
{"pulled_at": "2019-04-03", "Author": "Pengyuan Li"}
{"pulled_at": "2019-04-03", "Author": "WSP19SCM39H"}
{"pulled_at": "2019-04-03", "Author": "Pengyuan Li"}
{"pulled_at": "2019-04-02", "Author": "Pengyuan Li"}
{"pulled_at": "2019-04-02", "Author": "Pengyuan Li"}
{"pulled_at": "2019-04-02", "Author": "Pengyuan Li"}
{"pulled_at": "2019-04-02", "Author": "Pengyuan Li"}
{"pulled_at": "2019-04-02", "Author": "Pengyuan Li"}
{"pulled_at": "2019-04-02", "Author": "Pengyuan Li"}
{"pulled_at": "2019-04-02", "Author": "Pengyuan Li"}
{"pulled_at": "2019-04-02", "Author": "Pengyuan Li"}
{"pulled_at": "2019-04-02", "Author": "Pengyuan Li"}
{"pulled_at": "2019-04-02", "Author": "Pengyuan Li"}
{"pulled_at": "2019-04-02", "Author": "Pengyuan Li"}
{"pulled_at": "2019-04-02", "Author": "Pengyuan Li"}
{"pulled_at": "2019-04-02", "Author": "Pengyuan Li"}
{"pulled_at": "2019-04-02", "Author": "Pengyuan Li"}
{"pulled_at": "2019-04-02", "Author": "Pengyuan Li"}
{"pulled_at": "2019-04-02", "Author": "Pengyuan Li"}
{"pulled_at": "2019-04-02", "Author": "Pengyuan Li"}
{"pulled_at": "2019-04-08", "Author": "YSP19SCM81M"}
{"pulled_at": "2019-04-01", "Author": "Pengyuan Li"}
{"pulled_at": "2019-04-01", "Author": "Pengyuan Li"}
{"pulled_at": "2019-04-01", "Author": "Pengyuan Li"}
{"pulled_at": "2019-04-01", "Author": "Pengyuan Li"}
{"pulled_at": "2019-04-01", "Author": "Pengyuan Li"}
{"pulled_at": "2019-04-01", "Author": "Pengyuan Li"}
{"pulled_at": "2019-04-01", "Author": "JSP19SCM59D"}
{"pulled_at": "2019-04-01", "Author": "MSP19SCM18H"}
{"pulled_at": "2019-04-01", "Author": "Pengyuan Li"}
{"pulled_at": "2019-04-01", "Author": "Pengyuan Li"}
{"pulled_at": "2019-04-01", "Author": "JSP19SCM59D"}
{"pulled_at": "2019-04-02", "Author": "YSP19SCM81M"}
